autovizwidget/__init__.py
autovizwidget/plotlygraphs/__init__.py
autovizwidget/plotlygraphs/areagraph.py
autovizwidget/plotlygraphs/bargraph.py
autovizwidget/plotlygraphs/datagraph.py
autovizwidget/plotlygraphs/graphbase.py
autovizwidget/plotlygraphs/graphrenderer.py
autovizwidget/plotlygraphs/linegraph.py
autovizwidget/plotlygraphs/piegraph.py
autovizwidget/plotlygraphs/scattergraph.py
autovizwidget/utils/__init__.py
autovizwidget/utils/configuration.py
autovizwidget/utils/constants.py
autovizwidget/utils/events.py
autovizwidget/widget/__init__.py
autovizwidget/widget/autovizwidget.py
autovizwidget/widget/encoding.py
autovizwidget/widget/encodingwidget.py
autovizwidget/widget/invalidencodingerror.py
autovizwidget/widget/utils.py
vnpt_autovizwidget-0.1.2.dist-info/LICENSE.md
vnpt_autovizwidget-0.1.2.dist-info/METADATA
vnpt_autovizwidget-0.1.2.dist-info/WHEEL
vnpt_autovizwidget-0.1.2.dist-info/top_level.txt
vnpt_autovizwidget-0.1.2.dist-info/RECORD
