Metadata-Version: 2.1
Name: vnpt-autovizwidget
Version: 0.1.2
Summary: AutoVizWidget: An Auto-Visualization library for pandas dataframes
Home-page: https://github.com/jupyter-incubator/sparkmagic
Download-URL: https://github.com/jupyter-incubator/sparkmagic
Author: Jupyter Development Team
Author-email: jupyter@googlegroups.org
License: BSD 3-clause
Classifier: Development Status :: 4 - Beta
Classifier: Environment :: Console
Classifier: Intended Audience :: Science/Research
Classifier: License :: OSI Approved :: BSD License
Classifier: Natural Language :: English
Classifier: Programming Language :: Python :: 3.7
License-File: LICENSE.md
Requires-Dist: plotly>=3
Requires-Dist: ipywidgets>5.0.0
Requires-Dist: vnpt-hdijupyterutils==0.1.1
Requires-Dist: notebook>=4.2
Requires-Dist: pandas<3.0.0
